cu_roi/__init__.py
cu_roi/__main__.py
cu_stats-0.1.0.dist-info/LICENSE
cu_stats-0.1.0.dist-info/METADATA
cu_stats-0.1.0.dist-info/WHEEL
cu_stats-0.1.0.dist-info/top_level.txt
cu_stats-0.1.0.dist-info/RECORD
