Metadata-Version: 2.1
Name: cu-stats
Version: 0.1.0
Summary: Что-то считаем :)
Author-email: Pavel <p.glazunov@edu.centarlunivercity.ru>
License: MIT
Requires-Python: >=3.12
License-File: LICENSE
